webimg_square/__init__.py
webimg_square/cli.py
webimg_square-1.0.0.dist-info/licenses/LICENSE
webimg_square-1.0.0.dist-info/METADATA
webimg_square-1.0.0.dist-info/WHEEL
webimg_square-1.0.0.dist-info/entry_points.txt
webimg_square-1.0.0.dist-info/top_level.txt
webimg_square-1.0.0.dist-info/RECORD
