Metadata-Version: 2.4
Name: webimg-square
Version: 1.0.0
Summary: CLI tool to square images for web with smart padding
Author-email: Author <author@example.com>
License: MIT
Project-URL: Homepage, https://github.com/author/webimg-square
Project-URL: Repository, https://github.com/author/webimg-square
Project-URL: Issues, https://github.com/author/webimg-square/issues
Keywords: image,processing,cli,square,resize,web
Classifier: Development Status :: 5 - Production/Stable
Classifier: Environment :: Console
Classifier: Intended Audience :: Developers
Classifier: License :: OSI Approved :: MIT License
Classifier: Operating System :: OS Independent
Classifier: Programming Language :: Python :: 3
Classifier: Programming Language :: Python :: 3.8
Classifier: Programming Language :: Python :: 3.9
Classifier: Programming Language :: Python :: 3.10
Classifier: Programming Language :: Python :: 3.11
Classifier: Programming Language :: Python :: 3.12
Classifier: Topic :: Multimedia :: Graphics :: Graphics Conversion
Requires-Python: >=3.8
License-File: LICENSE
Requires-Dist: Pillow>=10.0.0
Requires-Dist: numpy>=1.24.0
Provides-Extra: dev
Requires-Dist: pytest>=7.0.0; extra == "dev"
Requires-Dist: pytest-cov>=4.0.0; extra == "dev"
Dynamic: license-file
